kicksaw_github_secrets_management/__init__.py
kicksaw_github_secrets_management/cli.py
kicksaw_github_secrets_management/script.py
kicksaw_github_secrets_management-0.0.1.dist-info/entry_points.txt
kicksaw_github_secrets_management-0.0.1.dist-info/WHEEL
kicksaw_github_secrets_management-0.0.1.dist-info/METADATA
kicksaw_github_secrets_management-0.0.1.dist-info/RECORD
