Metadata-Version: 2.1
Name: kicksaw-github-secrets-management
Version: 0.0.1
Summary: Provides a cli command for pushing secrets to a GitHub repo.
Home-page: https://github.com/Kicksaw-Consulting/kicksaw-github-secrets-management
Keywords: kicksaw,github,secrets
Author: Alex Drozd
Author-email: alex@kicksaw.com
Requires-Python: >=3.8,<4.0
Classifier: Programming Language :: Python :: 3
Classifier: Programming Language :: Python :: 3.10
Classifier: Programming Language :: Python :: 3.8
Classifier: Programming Language :: Python :: 3.9
Requires-Dist: PyGithub (>=1.55,<2.0)
Requires-Dist: PyNaCl (>=1.5.0,<2.0.0)
Requires-Dist: click (>=8.1.1,<9.0.0)
Project-URL: Repository, https://github.com/Kicksaw-Consulting/kicksaw-github-secrets-management
